annif/__init__.py
annif/analyzer/__init__.py
annif/analyzer/analyzer.py
annif/analyzer/estnltk.py
annif/analyzer/simple.py
annif/analyzer/simplemma.py
annif/analyzer/snowball.py
annif/analyzer/spacy.py
annif/analyzer/voikko.py
annif/backend/__init__.py
annif/backend/backend.py
annif/backend/dummy.py
annif/backend/ensemble.py
annif/backend/fasttext.py
annif/backend/http.py
annif/backend/hyperopt.py
annif/backend/mixins.py
annif/backend/mllm.py
annif/backend/nn_ensemble.py
annif/backend/omikuji.py
annif/backend/pav.py
annif/backend/stwfsa.py
annif/backend/svc.py
annif/backend/tfidf.py
annif/backend/yake.py
annif/cli.py
annif/cli_util.py
annif/config.py
annif/corpus/__init__.py
annif/corpus/combine.py
annif/corpus/document.py
annif/corpus/json.py
annif/corpus/types.py
annif/datadir.py
annif/default_config.py
annif/eval.py
annif/exception.py
annif/hfh_util.py
annif/lexical/__init__.py
annif/lexical/mllm.py
annif/lexical/tokenset.py
annif/lexical/util.py
annif/openapi/__init__.py
annif/openapi/annif.yaml
annif/openapi/validation.py
annif/parallel.py
annif/project.py
annif/registry.py
annif/rest.py
annif/schemas/document.json
annif/simplemma_util.py
annif/static/css/bootstrap.min.css
annif/static/css/bootstrap.min.css.map
annif/static/css/fonts.css
annif/static/css/style.css
annif/static/favicon.ico
annif/static/fonts/Jost-400-Book.otf
annif/static/fonts/Jost-400-Book.ttf
annif/static/fonts/Jost-500-Medium.otf
annif/static/fonts/Jost-500-Medium.ttf
annif/static/img/annif-RGB.svg
annif/static/img/arrow-white.svg
annif/static/js/axios.min.js
annif/static/js/axios.min.js.map
annif/static/js/bootstrap.min.js
annif/static/js/bootstrap.min.js.map
annif/static/js/vue.min.js
annif/suggestion.py
annif/templates/home.html
annif/transform/__init__.py
annif/transform/inputlimiter.py
annif/transform/langfilter.py
annif/transform/select.py
annif/transform/transform.py
annif/util.py
annif/views.py
annif/vocab/__init__.py
annif/vocab/rules.py
annif/vocab/skos.py
annif-1.4.1.dist-info/METADATA
annif-1.4.1.dist-info/WHEEL
annif-1.4.1.dist-info/entry_points.txt
annif-1.4.1.dist-info/licenses/LICENSE.txt
annif-1.4.1.dist-info/RECORD
