Metadata-Version: 2.4
Name: annif
Version: 1.4.1
Summary: Automated subject indexing and classification tool
License-Expression: Apache-2.0
License-File: LICENSE.txt
Keywords: machine-learning,text-classification,multilabel-classification,rest-api,code4lib,subject-indexing
Author: National Library of Finland
Author-email: finto-posti@helsinki.fi
Maintainer: Osma Suominen
Maintainer-email: osma.suominen@helsinki.fi
Requires-Python: >=3.10,<3.14
Classifier: Programming Language :: Python :: 3
Classifier: License :: OSI Approved :: Apache Software License
Classifier: Operating System :: OS Independent
Classifier: Development Status :: 5 - Production/Stable
Provides-Extra: estnltk
Provides-Extra: fasttext
Provides-Extra: nn
Provides-Extra: omikuji
Provides-Extra: spacy
Provides-Extra: stwfsa
Provides-Extra: voikko
Provides-Extra: yake
Requires-Dist: click (>=8.2.1,<8.3.0)
Requires-Dist: click-log (==0.4.*)
Requires-Dist: connexion[flask,swagger-ui,uvicorn] (>=3.1.0,<3.2.0)
Requires-Dist: estnltk (==1.7.4) ; extra == "estnltk"
Requires-Dist: fasttext-numpy2 (==0.10.4) ; extra == "fasttext"
Requires-Dist: gunicorn (>=23.0.0,<23.1.0)
Requires-Dist: huggingface-hub (>=0.34.4,<0.35.0)
Requires-Dist: joblib (>=1.5.1,<1.6.0)
Requires-Dist: jsonschema (>=4.25.0,<4.26.0)
Requires-Dist: lmdb (>=1.7.3,<1.8.0) ; extra == "nn"
Requires-Dist: nltk (>=3.9.1,<3.10.0)
Requires-Dist: numpy (>=2.2.6,<2.3.0)
Requires-Dist: omikuji (==0.5.*) ; extra == "omikuji"
Requires-Dist: optuna (>=4.5.0,<4.6.0)
Requires-Dist: python-dateutil (==2.9.*)
Requires-Dist: rdflib (>=7.1.3,<7.2.0)
Requires-Dist: requests (>=2.32.3,<2.33.0)
Requires-Dist: scikit-learn (>=1.7.1,<1.8.0)
Requires-Dist: scipy (>=1.15.3,<1.16.0)
Requires-Dist: simplemma (>=1.1.1,<1.2.0)
Requires-Dist: spacy (>=3.8.4,<3.9.0) ; extra == "spacy"
Requires-Dist: stwfsapy (>=0.6.1,<0.7.0) ; extra == "stwfsa"
Requires-Dist: tensorflow-cpu (>=2.20.0,<2.21.0) ; extra == "nn"
Requires-Dist: tomli (>=2.2.1,<2.3.0) ; python_version < "3.11"
Requires-Dist: voikko (==0.5.*) ; extra == "voikko"
Requires-Dist: yake (>=0.6.0,<0.7.0) ; extra == "yake"
Project-URL: Documentation, https://github.com/NatLibFi/Annif/wiki
Project-URL: Homepage, https://annif.org
Project-URL: Repository, https://github.com/NatLibFi/Annif
